genomeshader-0.1.91.dist-info/METADATA
genomeshader-0.1.91.dist-info/WHEEL
genomeshader-0.1.91.dist-info/licenses/LICENSE
genomeshader/__init__.py
genomeshader/genomeshader.abi3.so
genomeshader/html/instanced-renderer.js
genomeshader/html/sankey-renderer.js
genomeshader/html/template.html
genomeshader/html/text-renderer.js
genomeshader/html/tubemap-renderer.js
genomeshader/html/webgpu-core.js
genomeshader/staging.py
genomeshader/view.py
genomeshader-0.1.91.dist-info/RECORD
