Metadata-Version: 2.4
Name: genomeshader
Version: 0.1.91
Requires-Dist: polars
Requires-Dist: requests
Requires-Dist: requests-cache
License-File: LICENSE
Home-Page: https://github.com/broadinstitute/genomeshader
